{"kuO1qKGFI/Ih70mKWUDytg==":"logo-gocarbo_verde-escuro-e-branco-vert-96x54.png","cXtQu/sulQHAsLPjRIteAg==":"logo-gocarbo_verde-escuro-e-preto-vert-301x177.png","4toVEg4O3hhPV3i9AXFihQ==":"logo%20gocarbo_verde%20escuro%20e%20preto-272x75.png","TIy8PegmR48CHKByiwZMbQ==":"logo%20gocarbo_verde%20claro%20com%20preto-696x191.png","U02MTMVZ2rqTB1744iAINA==":"logo%20gocarbo_verde%20escuro%20e%20preto-932x256.png","ziFE+4TQ/dURXsSRMeCnAA==":"view-amazon-region-2000x1333.jpg","pL2sN9AVKAhbU5vxgU0nlA==":"mbr-1920x1277.jpg","Pt9M1fyNw2QbDx2zwmlMyw==":"mbr-1920x1439.jpg","BBHqF4V3oHiOLwYyQxw91Q==":"drone-with-camera-beautiful-summer-small-river-from-height-2000x1124.jpg","zkx9IdQpmMOMT9C/LW7uzg==":"screenshot-3-917x234.png","2aWVWhyfdL7HLHItL96+Wg==":"screenshot-2-696x142.png","SnZpq6MXWlUUCqWLKkv9kA==":"screenshot-2-920x188.png","8PSboFRjt2a0zK1VMQ18AQ==":"screenshot-1-696x137.png","pYwkoTGcS1ClMnqSbSYckQ==":"screenshot-1-920x181.png","LTebP8HUmLMBDf+nYTILtw==":"screenshot-4-625x218.png","MRHi7lNsJl5D21mpw/vz+w==":"screenshot-2-790x159.png","CyPHL7TgIjqltbCpJvwoAQ==":"beautiful-aerial-view-with-green-forest-landscape-twilight-2000x1500.jpg","LFp8lT3grANtWeZOBcgr9A==":"selective-focus-shot-toucan-standing-tree-branch-2000x1333.jpg","YRvBPE6VF9Ms73nEuJctlQ==":"selective-focus-shot-toucan-standing-tree-branch-2-1920x1536.png","MdlmeoNAbysCFkXntJTm6Q==":"hyacinth-macaw-palm-tree-nature-habitat-2076x1384.jpg","8MmRE586gG6djmTtRp3pfw==":"big-massive-iceberg-floating-ocean-2000x1306.jpg","3y6jDqMOBV64gE7QIvnffw==":"mystical-green-forest-brazil-2000x1325.jpg","U2XdulOhELh/VielO4cmCw==":"screenshot-6-635x149.png","MRgkOgJpPPkva4pd8oM6XQ==":"screenshot-7-1256x259.png","IwNNOKuP+qMtsdE9czgf+A==":"screenshot-8-984x203.png","oRykAiO0rUD++7AmPeEwUg==":"background1.jpg","JxxQCBIs1qSAsSFQdSJ4sg==":"ethereum-300x168.png","redcqQnPrX4f4me9P+raNQ==":"oracle-300x200.png","sd9lPQVdLDqq3JS2FHTuIg==":"aws-300x200.png","n9GxZ6sI7E8WOEGsaIKXwQ==":"binance-300x200.png","j+Tk7dysIxukGVGe4c/IgA==":"ethereum-300x200.png","Jm3wMFKHbc3DDX4of+ULzw==":"geraldo-213x215.jpg","veVJol1273Cn5xEkmL3Enw==":"gil-214x221.jpg","iHRkFI+KiB0sgP6EAIOeXA==":"tatiana-212x219.jpg","Ao5lZGK+eE/mSVuwWd6aCA==":"wender-212x219.jpg","SZLXTXoLzX4feG/dZbnfwQ==":"walace-213x218.jpg","mnUhFCogPLK/uxXQT3dQlQ==":"nender-212x217.jpg","y/lTsui+Ja+8dA147wEHaA==":"alexandre-212x216.jpg","dQ9hRzkGUwlfw6BTMo5eKg==":"leo-213x223.jpg","nCz6Yhswuztr/6BWfRLA0g==":"voce-214x217.jpg","po9KAjbEjV/E2mPAa78pQg==":"payagil-300x200.png","R9Lc30o7cMxuu6IB2GB5LA==":"wl-connections-300x200.png","C4/Eg3n+P86sHmfR300YsA==":"global-300x200.png","PGO2rxSzePgepLcbvBnK0A==":"geraldo-421x429.png","IcgCjZ5xt06gPGCOohAtkQ==":"gil-424x433.png","0CL3B2KuVSLwk/0VywGVuQ==":"tatiana-423x432.png","s8+g1+7omXLo96ziaKqFig==":"wender-421x432.png","3PzpM5XOp7kHB1D5rJvbfQ==":"walace-423x433.png","mbt0kjPUtGy5GloXnIbF0g==":"walace-816x818.png","n+Vc/sGhC5tn9e3YTk1Kgg==":"nenger-419x433.png","VNkmxFbLD9rfXrmPcqAkZg==":"alexandre-423x425.png","901K2SF8blQCDPu7vim/Bg==":"leo-638x636.png"}